tmo_api/__init__.py
tmo_api/_version.py
tmo_api/client.py
tmo_api/environments.py
tmo_api/exceptions.py
tmo_api/cli/__init__.py
tmo_api/cli/tmoapi.py
tmo_api/cli/tmolo.py
tmo_api/cli/tmols.py
tmo_api/cli/tmopo.py
tmo_api/models/__init__.py
tmo_api/models/base.py
tmo_api/models/pool.py
tmo_api/resources/__init__.py
tmo_api/resources/certificates.py
tmo_api/resources/distributions.py
tmo_api/resources/history.py
tmo_api/resources/partners.py
tmo_api/resources/pools.py
tmo_api/assets/postman_collection/tmo_api_collection_20250801.json
tmo_api/assets/postman_collection/tmo_api_collection_20250808.json
tmo_api/assets/postman_collection/tmo_api_collection_20251003.json
tmo_api/assets/postman_collection/tmo_api_collection_20251101.json
tmo_api/assets/postman_collection/tmo_api_collection_20251117.json
tmo_api-0.1.3.dist-info/METADATA
tmo_api-0.1.3.dist-info/WHEEL
tmo_api-0.1.3.dist-info/entry_points.txt
tmo_api-0.1.3.dist-info/licenses/LICENSE
tmo_api-0.1.3.dist-info/RECORD
